setup.py
pymongogo/__init__.py
pymongogo/model.py
pymongogo.egg-info/PKG-INFO
pymongogo.egg-info/SOURCES.txt
pymongogo.egg-info/dependency_links.txt
pymongogo.egg-info/not-zip-safe
pymongogo.egg-info/requires.txt
pymongogo.egg-info/top_level.txt