Metadata-Version: 1.0
Name: pymongogo
Version: 0.4
Summary: A Pymongo wrapper
Home-page: https://bitbucket.org/mattbodman/pymongogo/src
Author: Matt Bodman
Author-email: mattbodman@gmail.com
License: UNKNOWN
Platform: UNKNOWN
